nada_mir_proto/__init__.py
nada_mir_proto/nillion/__init__.py
nada_mir_proto/nillion/nada/__init__.py
nada_mir_proto/nillion/nada/mir/__init__.py
nada_mir_proto/nillion/nada/mir/v1/__init__.py
nada_mir_proto/nillion/nada/operations/__init__.py
nada_mir_proto/nillion/nada/operations/v1/__init__.py
nada_mir_proto/nillion/nada/types/__init__.py
nada_mir_proto/nillion/nada/types/v1/__init__.py
nada_mir_proto-0.2.0.dist-info/METADATA
nada_mir_proto-0.2.0.dist-info/WHEEL
nada_mir_proto-0.2.0.dist-info/top_level.txt
nada_mir_proto-0.2.0.dist-info/RECORD
